protonvpn_linux_gui/__init__.py
protonvpn_linux_gui/__main__.py
protonvpn_linux_gui/constants.py
protonvpn_linux_gui/gui.py
protonvpn_linux_gui/gui_logger.py
protonvpn_linux_gui/thread_functions.py
protonvpn_linux_gui/tray_icon.py
protonvpn_linux_gui/utils.py
protonvpn_linux_gui/resources/__init__.py
protonvpn_linux_gui/resources/main.css
protonvpn_linux_gui/resources/main.glade
protonvpn_linux_gui/resources/img/flags/__init__.py
protonvpn_linux_gui/resources/img/flags/large/__init__.py
protonvpn_linux_gui/resources/img/flags/large/ad.jpg
protonvpn_linux_gui/resources/img/flags/large/ae.jpg
protonvpn_linux_gui/resources/img/flags/large/af.jpg
protonvpn_linux_gui/resources/img/flags/large/ag.jpg
protonvpn_linux_gui/resources/img/flags/large/al.jpg
protonvpn_linux_gui/resources/img/flags/large/am.jpg
protonvpn_linux_gui/resources/img/flags/large/ao.jpg
protonvpn_linux_gui/resources/img/flags/large/ar.jpg
protonvpn_linux_gui/resources/img/flags/large/at.jpg
protonvpn_linux_gui/resources/img/flags/large/au.jpg
protonvpn_linux_gui/resources/img/flags/large/az.jpg
protonvpn_linux_gui/resources/img/flags/large/ba.jpg
protonvpn_linux_gui/resources/img/flags/large/bb.jpg
protonvpn_linux_gui/resources/img/flags/large/bd.jpg
protonvpn_linux_gui/resources/img/flags/large/be.jpg
protonvpn_linux_gui/resources/img/flags/large/bf.jpg
protonvpn_linux_gui/resources/img/flags/large/bg.jpg
protonvpn_linux_gui/resources/img/flags/large/bh.jpg
protonvpn_linux_gui/resources/img/flags/large/bi.jpg
protonvpn_linux_gui/resources/img/flags/large/bj.jpg
protonvpn_linux_gui/resources/img/flags/large/bn.jpg
protonvpn_linux_gui/resources/img/flags/large/bo.jpg
protonvpn_linux_gui/resources/img/flags/large/br.jpg
protonvpn_linux_gui/resources/img/flags/large/bs.jpg
protonvpn_linux_gui/resources/img/flags/large/bt.jpg
protonvpn_linux_gui/resources/img/flags/large/bw.jpg
protonvpn_linux_gui/resources/img/flags/large/by.jpg
protonvpn_linux_gui/resources/img/flags/large/bz.jpg
protonvpn_linux_gui_calexandru2018-2.0.7.dist-info/LICENSE
protonvpn_linux_gui_calexandru2018-2.0.7.dist-info/METADATA
protonvpn_linux_gui_calexandru2018-2.0.7.dist-info/WHEEL
protonvpn_linux_gui_calexandru2018-2.0.7.dist-info/entry_points.txt
protonvpn_linux_gui_calexandru2018-2.0.7.dist-info/top_level.txt
protonvpn_linux_gui_calexandru2018-2.0.7.dist-info/RECORD
