Metadata-Version: 2.1
Name: protonvpn-linux-gui-calexandru2018
Version: 2.0.7
Summary: Unofficial Linux GUI client for ProtonVPN
Home-page: https://github.com/calexandru2018/protonvpn-linux-gui
Author: calexandru2018
Author-email: acrandom@pm.me
License: GPLv3
Platform: UNKNOWN
Classifier: Development Status :: 4 - Beta
Classifier: Environment :: Console
Classifier: Environment :: X11 Applications :: GTK
Classifier: Intended Audience :: End Users/Desktop
Classifier: Operating System :: POSIX :: Linux
Classifier: License :: OSI Approved :: GNU General Public License v3 (GPLv3)
Classifier: Programming Language :: Python
Classifier: Programming Language :: Python :: 3 :: Only
Classifier: Programming Language :: Python :: 3.5
Classifier: Programming Language :: Python :: 3.6
Classifier: Programming Language :: Python :: 3.7
Classifier: Programming Language :: Python :: 3.8
Requires-Python: >=3.5
Requires-Dist: protonvpn-cli (>=2.2.2)
Requires-Dist: requests (>=2.23.0)
Requires-Dist: configparser (>=4.0.2)
